gwas_tools/__init__.py
gwas_tools/algorithms/__init__.py
gwas_tools/algorithms/scattered_light.py
gwas_tools/algorithms/scattered_light_gwf.py
gwas_tools/algorithms/scattered_light_raw.py
gwas_tools/automation/__init__.py
gwas_tools/automation/scripts.py
gwas_tools/common/__init__.py
gwas_tools/common/defines.py
gwas_tools/helpers/__init__.py
gwas_tools/helpers/dag_file.py
gwas_tools/helpers/fetch_params.py
gwas_tools/helpers/sub_file.py
gwas_tools/html/__init__.py
gwas_tools/html/html_builder.py
gwas_tools/summary_pages/__init__.py
gwas_tools/summary_pages/daily_correlations_page.py
gwas_tools/summary_pages/scattered_light_page.py
gwas_tools/utils/__init__.py
gwas_tools/utils/file_utils.py
gwas_tools/utils/plot_utils.py
gwas_tools/utils/signal_utils.py
gwas_tools-0.14.8.dist-info/LICENSE
gwas_tools-0.14.8.dist-info/METADATA
gwas_tools-0.14.8.dist-info/WHEEL
gwas_tools-0.14.8.dist-info/top_level.txt
gwas_tools-0.14.8.dist-info/RECORD
