Metadata-Version: 2.1
Name: gwas_tools
Version: 0.14.8
Summary: Utils functions to build a pipeline for scattered light noise hunting in gravitational waves detectors.
Home-page: https://github.com/FisicaTre/gwas_tools
Author: Stefano Bianchi, Alessandro Longo, Guillermo Valdes
Author-email: stefanobianchi9@gmail.com
License: GPLv3.0
Project-URL: Bug Reports, https://github.com/FisicaTre/gwas_tools/issues
Project-URL: Source, https://github.com/FisicaTre/gwas_tools
Classifier: License :: OSI Approved :: GNU General Public License v3 (GPLv3)
Classifier: Operating System :: OS Independent
Classifier: Programming Language :: Python :: 3
Classifier: Topic :: Scientific/Engineering
Requires-Python: >=3.7
License-File: LICENSE
Requires-Dist: numpy >=1.15
Requires-Dist: gwpy
Requires-Dist: gwdetchar
Requires-Dist: MarkupPy
Requires-Dist: pytz
Requires-Dist: pandas
Requires-Dist: scipy
Requires-Dist: pyYAML
Requires-Dist: matplotlib
Requires-Dist: astropy
Requires-Dist: pytvfemd >=0.3.12
